[
    {
        "id":1,
        "fmain":"Calendar connections per person",
        "fbody":
            {
                "Free": 1,
                "Basic": 2,
                "Pro": 6,
                "Team": 6,
                "Enterprise": 6
               }
       
    }
    ,
    {
        "id":2,
        "fmain":"Connect to Google, Office 365, Outlook, and iCloud calendars",
        "fbody":
            {
                "Free": "Yes",
                "Basic": "Yes",
                "Pro": "Yes",
                "Team": "Yes",
                "Enterprise": "Yes"
               }
       
    }
    ,
    {
        "id":3,
        "fmain":"Access Calendly with web, iOS, and Android apps",
        "fbody":
            {
               
                "Free": "Yes",
                "Basic": "Yes",
                "Pro": "Yes",
                "Team": "Yes",
                "Enterprise": "Yes"
               }
       
    }
    ,
    {
        "id":4,
        "fmain":"Active event types",
        "fbody":
            {
                "Free": 1,
                "Basic": "Unlimited",
                "Pro": "Unlimited",
                "Team": "Unlimited",
                "Enterprise": "Unlimited"
               }
       
    }
    ,
    {
        "id":5,
        "fmain":"Create unlimited one-on-one events",
        "fbody":
            {
                "Free": "No",
                "Basic": "Yes",
                "Pro": "Yes",
                "Team": "Yes",
                "Enterprise": "Yes"
               }
       
    }
    ,
    {
        "id":6,
        "fmain":"Create meeting polls",
        "fbody":
            {
                "Free": "Unlimited",
                "Basic": "Unlimited",
                "Pro": "Unlimited",
                "Team": "Unlimited",
                "Enterprise": "Unlimited"
               }
       
    }
    ,
    {
        "id":7,
        "fmain":"Create one-off meetings",
        "fbody":
            {
                "Free": "Unlimited",
                "Basic": "Unlimited",
                "Pro": "Unlimited",
                "Team": "Unlimited",
                "Enterprise": "Unlimited"
               }
       
    }
    ,
    {
        "id":8,
        "fmain":"Collective one-offs",
        "fbody":
            {
                "Free": "No",
                "Basic": "No",
                "Pro": "No",
                "Team": "Yes",
                "Enterprise": "Yes"
               }
       
    }
    ,
    {
        "id":9,
        "fmain":"Customize your booking link",
        "fbody":
            {
                "Free": "No",
                "Basic": "Yes",
                "Pro": "Yes",
                "Team": "Yes",
                "Enterprise": "Yes"
               }
       
    }
    ,
    {
        "id":10,
        "fmain":"Create group events",
        "fbody":
            {
                "Free": "No",
                "Basic": "No",
                "Pro": "No",
                "Team": "Yes",
                "Enterprise": "Yes"
               }
       
    }
    ,
    {
        "id":11,
        "fmain":"Automated event notifications",
        "fbody":
            {
                "Free": "No",
                "Basic": "Yes",
                "Pro": "Yes",
                "Team": "Yes",
                "Enterprise": "Yes"
               }
       
    }
    ,
    {
        "id":12,
        "fmain":"Send your invitee email reminders and follow-ups",
        "fbody":
            {
                "Free": "No",
                "Basic": "Yes",
                "Pro": "Yes",
                "Team": "Yes",
                "Enterprise": "Yes"
               }
       
    }
    ,
    {
        "id":13,
        "fmain":"Customize email notifications and reminders",
        "fbody":
            {
                "Free": "No",
                "Basic": "No",
                "Pro": "Yes",
                "Team": "Yes",
                "Enterprise": "Yes"
               }
       
    }
    ,
    {
        "id":14,
        "fmain":"Get meeting notifications via text",
        "fbody":
            {
                "Free": "No",
                "Basic": "No",
                "Pro": "No",
                "Team": "Yes",
                "Enterprise": "Yes"
               }
       
    }
    ,
    {
        "id":15,
        "fmain":"Update your cancellation policy",
        "fbody":
            {
                "Free": "No",
                "Basic": "No",
                "Pro": "Yes",
                "Team": "Yes",
                "Enterprise": "Yes"
               }
       
    }
    ,
    {
        "id":16,
        "fmain":"Create automated workflows",
        "fbody":
            {
                "Free": "No",
                "Basic": "No",
                "Pro": "No",
                "Team": "Yes",
                "Enterprise": "Yes"
               }
       
    }
    ,
    {
        "id":17,
        "fmain":"Add links to your confirmation pages",
        "fbody":
            {
                "Free": "No",
                "Basic": "No",
                "Pro": "No",
                "Team": "Yes",
                "Enterprise": "Yes"
               }
       
    }
    ,
    {
        "id":18,
        "fmain":"Redirect your invitees",
        "fbody":
            {
                "Free": "No",
                "Basic": "No",
                "Pro": "No",
                "Team": "Yes",
                "Enterprise": "Yes"
               }
       
    }
    ,
    {
        "id":19,
        "fmain":"View analytics and insights",
        "fbody":
            {
                "Free": "No",
                "Basic": "No",
                "Pro": "Yes",
                "Team": "Yes",
                "Enterprise": "Yes"
               }
       
    }
]
